admix/__init__.py
admix/admix.py
admix/clients.py
admix/downloader.py
admix/fix.py
admix/manager.py
admix/monitor.py
admix/rucio.py
admix/showrun.py
admix/uploader.py
admix/utils.py
admix/validator.py
admix/daemons/__init__.py
admix/daemons/daemon.py
admix/daemons/sync.py
admix/daemons/upload.py
admix/helper/__init__.py
admix/helper/decorator.py
admix/helper/helper.py
admix/interfaces/__init__.py
admix/interfaces/rucio_api.py
admix/interfaces/rucio_summoner.py
tests/__init__.py
tests/test_admix.py
xe_admix-1.0.15.data/scripts/admix-download
xe_admix-1.0.15.dist-info/AUTHORS.rst
xe_admix-1.0.15.dist-info/LICENSE
xe_admix-1.0.15.dist-info/METADATA
xe_admix-1.0.15.dist-info/WHEEL
xe_admix-1.0.15.dist-info/top_level.txt
xe_admix-1.0.15.dist-info/RECORD
