Metadata-Version: 2.1
Name: xe-admix
Version: 1.0.15
Summary: advanced Data Management In Xenon (aDMIX)
Home-page: https://github.com/XENON1T/admix
Author: UNKNOWN
Author-email: UNKNOWN
License: BSD license
Keywords: admix
Platform: UNKNOWN
Classifier: Development Status :: 2 - Pre-Alpha
Classifier: Intended Audience :: Developers
Classifier: License :: OSI Approved :: BSD License
Classifier: Natural Language :: English
Classifier: Programming Language :: Python :: 3.6
Requires-Dist: pymongo
Requires-Dist: tqdm
Requires-Dist: utilix
